tpdk_safe_checkout/__init__.py
tpdk_safe_checkout/api_client.py
tpdk_safe_checkout/api_response.py
tpdk_safe_checkout/configuration.py
tpdk_safe_checkout/exceptions.py
tpdk_safe_checkout/py.typed
tpdk_safe_checkout/rest.py
tpdk_safe_checkout/api/__init__.py
tpdk_safe_checkout/api/admin_api.py
tpdk_safe_checkout/api/branding_api.py
tpdk_safe_checkout/api/persona_api.py
tpdk_safe_checkout/api/safe_checkout_api.py
tpdk_safe_checkout/api/transaction_api.py
tpdk_safe_checkout/api/user_api.py
tpdk_safe_checkout/api/webhook_api.py
tpdk_safe_checkout/models/__init__.py
tpdk_safe_checkout/models/access_error.py
tpdk_safe_checkout/models/address.py
tpdk_safe_checkout/models/address_user_read.py
tpdk_safe_checkout/models/api_client_post_creation_read.py
tpdk_safe_checkout/models/api_client_read.py
tpdk_safe_checkout/models/api_client_write.py
tpdk_safe_checkout/models/auth_error.py
tpdk_safe_checkout/models/bank_account_read.py
tpdk_safe_checkout/models/bank_account_user_read.py
tpdk_safe_checkout/models/bank_account_write.py
tpdk_safe_checkout/models/card_collection_read.py
tpdk_safe_checkout/models/card_metadata_collection_read.py
tpdk_safe_checkout/models/card_metadata_read.py
tpdk_safe_checkout/models/card_metadata_update.py
tpdk_safe_checkout/models/card_read.py
tpdk_safe_checkout/models/card_update.py
tpdk_safe_checkout/models/card_user_read.py
tpdk_safe_checkout/models/card_write.py
tpdk_safe_checkout/models/cashout_cash_out_collection_read.py
tpdk_safe_checkout/models/cashout_cash_out_read.py
tpdk_safe_checkout/models/cashout_cash_out_write.py
tpdk_safe_checkout/models/generic_error.py
tpdk_safe_checkout/models/invalid_query_error.py
tpdk_safe_checkout/models/media.py
tpdk_safe_checkout/models/media_read.py
tpdk_safe_checkout/models/media_user_read.py
tpdk_safe_checkout/models/message_error.py
tpdk_safe_checkout/models/metadata.py
tpdk_safe_checkout/models/not_found_error.py
tpdk_safe_checkout/models/offer.py
tpdk_safe_checkout-2.0.109.dist-info/METADATA
tpdk_safe_checkout-2.0.109.dist-info/WHEEL
tpdk_safe_checkout-2.0.109.dist-info/top_level.txt
tpdk_safe_checkout-2.0.109.dist-info/RECORD
