Metadata-Version: 2.1
Name: tpdk-safe-checkout
Version: 2.0.109
Summary: Safe Checkout
Home-page: https://pypi.org/project/tpdk-safe-checkout
Author: Tripartie SAS
Author-email: noc@tripartie.com
Keywords: OpenAPI,OpenAPI-Generator,Safe Checkout
Requires-Dist: urllib3 <3.0.0,>=1.25.3
Requires-Dist: python-dateutil >=2.8.2
Requires-Dist: pydantic >=2
Requires-Dist: typing-extensions >=4.7.1
